SPI/8bit_echo/src/periph/pin_controller.v
module pin_controller (
	input wire clk,
	input wire [63:0] toggle_mask,
	input wire toggle_enable,
	output reg [63:0] output_pins
);

	initial output_pins = 64'b0;

	always @(posedge clk) begin
		if (toggle_enable) begin
			output_pins <= output_pins ^ toggle_mask;
		end
	end

endmodule

icoboard/ver1/tb/pin_controller_tb.v
`timescale 1ns / 1ps

module pin_controller_tb;

    // DUT inputs
    reg clk;
    reg toggle_enable;
    reg [63:0] toggle_mask;

    // DUT output
    wire [63:0] output_pins;

    // Instantiate DUT
    pin_controller uut (
        .clk(clk),
        .toggle_mask(toggle_mask),
        .toggle_enable(toggle_enable),
        .output_pins(output_pins)
    );

    // Clock generation: 50 MHz
    always #10 clk = ~clk;

    // Task to toggle a specific pin
    task toggle_pin(input [5:0] pin_index);
    	begin
		toggle_mask = 64'b1 << pin_index;
		toggle_enable = 1;

		@(posedge clk);
		#1;
		toggle_enable = 0;

		$display("Toggled pin %0d | out_pins = %b", pin_index, output_pins);
    	end
    endtask

    initial begin
        $display("Starting pin_controller testbench...");
        $dumpfile("pin_controller_tb.vcd");
        $dumpvars(0, pin_controller_tb);

        clk = 0;
        toggle_enable = 0;
        toggle_mask = 0;
        #20;

        toggle_pin(0);   // Toggle pin 0 ON
        toggle_pin(3);   // Toggle pin 3 ON
        toggle_pin(0);   // Toggle pin 0 OFF
        toggle_pin(63);  // Toggle pin 63 ON
        toggle_pin(63);  // Toggle pin 63 OFF

        #50;
        $display("Final out_pins = %b", output_pins);
        $finish;
    end

endmodule

SPI/8bit_echo/src/periph/pin_controller_tb.vcd
$date
	Sun Mar 30 16:13:40 2025
$end
$version
	Icarus Verilog
$end
$timescale
	1ps
$end
$scope module pin_controller_tb $end
$var wire 64 ! output_pins [63:0] $end
$var reg 1 " clk $end
$var reg 1 # toggle_enable $end
$var reg 64 $ toggle_mask [63:0] $end
$scope module uut $end
$var wire 1 " clk $end
$var wire 1 # toggle_enable $end
$var wire 64 % toggle_mask [63:0] $end
$var reg 64 & output_pins [63:0] $end
$upscope $end
$scope task toggle_pin $end
$var reg 6 ' pin_index [5:0] $end
$upscope $end
$upscope $end
$enddefinitions $end
#0
$dumpvars
bx '
b0 &
b0 %
b0 $
0#
0"
b0 !
$end
#10000
1"
#20000
0"
1#
b1 $
b1 %
b0 '
#30000
b1 !
b1 &
1"
#31000
b1000 $
b1000 %
b11 '
1#
#40000
0"
#50000
b1001 !
b1001 &
1"
#51000
b1 $
b1 %
b0 '
1#
#60000
0"
#70000
b1000 !
b1000 &
1"
#71000
b1000000000000000000000000000000000000000000000000000000000000000 $
b1000000000000000000000000000000000000000000000000000000000000000 %
b111111 '
1#
#80000
0"
#90000
b1000000000000000000000000000000000000000000000000000000000001000 !
b1000000000000000000000000000000000000000000000000000000000001000 &
1"
#91000
1#
#100000
0"
#110000
b1000 !
b1000 &
1"
#111000
0#
