SPI/8bit_echo/src/periph/decoder.v
module decoder (
	input wire byte_ready,
	input wire [7:0] command_byte,
	output reg [63:0] toggle_mask
);

	always @(posedge byte_ready) begin
		toggle_mask <= 64'b1 << command_byte[5:0];
	end

endmodule

icoboard/ver1/tb/decoder_tb.v
`timescale 1ns / 1ps

module decoder_tb;

    // DUT inputs
    reg [7:0] command_byte;
    reg byte_ready;

    // DUT output
    wire [63:0] toggle_mask;

    // Instantiate the DUT
    decoder uut (
        .command_byte(command_byte),
        .byte_ready(byte_ready),
        .toggle_mask(toggle_mask)
    );

    // Task to test a single byte
    task test_command(input [7:0] cmd);
        begin
            command_byte = cmd;
            byte_ready = 1;
            #1;
            byte_ready = 0;
            #1;
            $display("Command: 0x%h | Index: %0d | Toggle Mask: %b", cmd, cmd[5:0], toggle_mask);
        end
    endtask

    initial begin
        $display("Starting decoder testbench...");
        $dumpfile("decoder_tb.vcd");
        $dumpvars(0, decoder_tb);

        byte_ready = 0;
        command_byte = 0;
        #5;

        test_command(8'h00);  // Should set bit 0
        test_command(8'h01);  // Should set bit 1
        test_command(8'h3F);  // Should set bit 63
        test_command(8'hA5);  // Bit 37
        test_command(8'hFF);  // Lower 6 bits = 63 again

        #10;
        $finish;
    end

endmodule

icoboard/ver1/tb/decoder_tb.vcd
$date
	Wed Apr  9 10:43:07 2025
$end
$version
	Icarus Verilog
$end
$timescale
	1ps
$end
$scope module decoder_tb $end
$var wire 64 ! toggle_mask [63:0] $end
$var reg 1 " byte_ready $end
$var reg 8 # command_byte [7:0] $end
$scope module uut $end
$var wire 1 " byte_ready $end
$var wire 8 $ command_byte [7:0] $end
$var reg 64 % toggle_mask [63:0] $end
$upscope $end
$scope task test_command $end
$var reg 8 & cmd [7:0] $end
$upscope $end
$upscope $end
$enddefinitions $end
#0
$dumpvars
bx &
bx %
b0 $
b0 #
0"
bx !
$end
#5000
b1 !
b1 %
1"
b0 &
#6000
0"
#7000
b10 !
b10 %
1"
b1 #
b1 $
b1 &
#8000
0"
#9000
b1000000000000000000000000000000000000000000000000000000000000000 !
b1000000000000000000000000000000000000000000000000000000000000000 %
1"
b111111 #
b111111 $
b111111 &
#10000
0"
#11000
b10000000000000000000000000000000000000 !
b10000000000000000000000000000000000000 %
1"
b10100101 #
b10100101 $
b10100101 &
#12000
0"
#13000
b1000000000000000000000000000000000000000000000000000000000000000 !
b1000000000000000000000000000000000000000000000000000000000000000 %
1"
b11111111 #
b11111111 $
b11111111 &
#14000
0"
