old/8bit_echo/src/periph/spi_rx.v
module spi_rx #(
parameter WIDTH = 8
)(
	input wire sclk,
	input wire cs,
	input wire mosi,
	output reg [WIDTH-1:0] command_byte,
	output reg byte_ready
);

	reg [WIDTH-1:0] shift_reg;
	reg [2:0] bit_count;

	always @(negedge sclk) begin
		shift_reg <= {shift_reg[WIDTH-2:0], mosi};
		bit_count <= bit_count + 1;

		if (bit_count == (WIDTH - 1)) begin
			command_byte <= shift_reg;
			byte_ready <= 1;
			$display("spi_rx: Received byte: %h", shift_reg);
		end else begin
			byte_ready <= 0;
		end
	end

	always @(posedge cs) begin
		shift_reg <= 0;
		bit_count <= 0;
		byte_ready <= 0;
	end

endmodule

icoboard/ver1/tb/spi_rx_tb.v
`timescale 1ns / 1ps

module spi_rx_tb;

    // Parameters
    parameter WIDTH = 8;

    // DUT Inputs
    reg sclk = 0;
    reg cs = 1;
    reg mosi = 0;

    // DUT Outputs
    wire [WIDTH-1:0] command_byte;
    wire byte_ready;

    // Instantiate the DUT (Device Under Test)
    spi_rx #(.WIDTH(WIDTH)) uut (
        .sclk(sclk),
        .cs(cs),
        .mosi(mosi),
        .command_byte(command_byte),
        .byte_ready(byte_ready)
    );

    // Task to send 1 byte over SPI (MSB first)
    task send_spi_byte(input [7:0] data);
        integer i;
        begin
	    cs = 0;
	    #5;
	    
            for (i = 7; i >= 0; i = i - 1) begin
		sclk = 0;
		#10
		mosi = data[i];

		sclk = 1;
		#10;
            end

	    sclk = 0;
	    #10
	    cs = 1;
	    #20;
        end
    endtask

    // Test sequence
    initial begin
        $display("Starting SPI RX Test");
        $dumpfile("spi_rx_tb.vcd");    // for waveform viewer
        $dumpvars(0, spi_rx_tb);
	
	cs = 1;
	#40;

        // Send first byte: 0xA5
        send_spi_byte(8'hA5);
	#40;

	// Send first byte: 0xB3
        send_spi_byte(8'hB3);
	#40;

        $display("Test complete");
        $finish;
    end

endmodule

icoboard/ver1/tb/spi_rx_tb.vcd
$date
	Sun Mar 30 12:29:22 2025
$end
$version
	Icarus Verilog
$end
$timescale
	1ps
$end
$scope module spi_rx_tb $end
$var wire 8 ! command_byte [7:0] $end
$var wire 1 " byte_ready $end
$var reg 1 # cs $end
$var reg 1 $ mosi $end
$var reg 1 % sclk $end
$scope module uut $end
$var wire 8 & command_byte [7:0] $end
$var wire 1 # cs $end
$var wire 1 $ mosi $end
$var wire 1 % sclk $end
$var reg 3 ' bit_count [2:0] $end
$var reg 1 " byte_ready $end
$var reg 8 ( shift_reg [7:0] $end
$upscope $end
$scope task send_spi_byte $end
$var reg 8 ) data [7:0] $end
$var integer 32 * i [31:0] $end
$upscope $end
$upscope $end
$enddefinitions $end
#0
$dumpvars
bx *
bx )
b0 (
b0 '
b0 &
0%
0$
1#
0"
b0 !
$end
#40000
0#
b10100101 )
#45000
b111 *
#55000
1%
1$
#65000
b1 '
b1 !
b1 &
b1 (
0%
b110 *
#75000
1%
0$
#85000
b10 '
b10 !
b10 &
b10 (
0%
b101 *
#95000
1%
1$
#105000
b11 '
b101 !
b101 &
b101 (
0%
b100 *
#115000
1%
0$
#125000
b100 '
b1010 !
b1010 &
b1010 (
0%
b11 *
#135000
1%
#145000
b101 '
b10100 !
b10100 &
b10100 (
0%
b10 *
#155000
1%
1$
#165000
b110 '
b101001 !
b101001 &
b101001 (
0%
b1 *
#175000
1%
0$
#185000
b111 '
b1010010 !
b1010010 &
b1010010 (
0%
b0 *
#195000
1%
1$
#205000
1"
b0 '
b10100101 !
b10100101 &
b10100101 (
0%
b11111111111111111111111111111111 *
#215000
0"
b0 !
b0 &
b0 (
1#
#275000
0#
b10110011 )
#280000
b111 *
#290000
1%
#300000
b1 '
b1 !
b1 &
b1 (
0%
b110 *
#310000
1%
0$
#320000
b10 '
b10 !
b10 &
b10 (
0%
b101 *
#330000
1%
1$
#340000
b11 '
b101 !
b101 &
b101 (
0%
b100 *
#350000
1%
#360000
b100 '
b1011 !
b1011 &
b1011 (
0%
b11 *
#370000
1%
0$
#380000
b101 '
b10110 !
b10110 &
b10110 (
0%
b10 *
#390000
1%
#400000
b110 '
b101100 !
b101100 &
b101100 (
0%
b1 *
#410000
1%
1$
#420000
b111 '
b1011001 !
b1011001 &
b1011001 (
0%
b0 *
#430000
1%
#440000
1"
b0 '
b10110011 !
b10110011 &
b10110011 (
0%
b11111111111111111111111111111111 *
#450000
0"
b0 !
b0 &
b0 (
1#
