icoboard/ver1/src/periph/pin_controller.v
module pin_controller (
	input wire clk,
	input wire [63:0] toggle_mask,
	input wire toggle_enable,
	output reg [63:0] output_pins
);

	initial output_pins = 64'b0;
	reg prev_toggle_enable;

	always @(posedge clk) begin
		if (~prev_toggle_enable && toggle_enable) begin
			output_pins <= output_pins ^ toggle_mask;
			$display("pin_controller: Toggling output_pins <= %b", output_pins ^ toggle_mask);
		end
		prev_toggle_enable <= toggle_enable;
	end

endmodule

SPI/8bit_echo/src/periph/decoder.v
module decoder (
	input wire byte_ready,
	input wire [7:0] command_byte,
	output reg [63:0] toggle_mask
);

	always @(posedge byte_ready) begin
		toggle_mask <= 64'b1 << command_byte[5:0];
	end

endmodule

icoboard/ver1/src/periph/spi_rx.v
module spi_rx #(
parameter WIDTH = 8
)(
	input wire sclk,
	input wire cs,
	input wire mosi,
	output reg [WIDTH-1:0] command_byte,
	output reg byte_ready
);

	reg [2:0] bit_count;

	always @(negedge sclk) begin
		command_byte <= {command_byte[WIDTH-2:0], mosi};
		bit_count <= bit_count + 1;

		if (bit_count == (WIDTH - 1)) begin
			byte_ready <= 1;
		end else begin
			byte_ready <= 0;
		end
	end

	always @(negedge cs) begin
		if (!cs) begin
			bit_count <= 0;
		end
	end

endmodule

old/8bit_echo/src/periph/top.v
module top (
    input wire  CLK,		// system clock (internal logic)
    input wire SCLK,		// SPI clock
    input wire  CS,		// Chip select (active low)
    input wire MOSI,		// Ctlr Out, Periph In
    output wire [63:0] pins	// Icoboard output pins
);

    wire [7:0] COMMAND_BYTE;
    wire BYTE_READY;
    wire [63:0] TOGGLE_MASK;

    // SPI RECEIVER INSTANCE
    spi_rx spi_receiver (
	    .sclk(SCLK),
	    .cs(CS),
	    .mosi(MOSI),
	    .command_byte(COMMAND_BYTE),
	    .byte_ready(BYTE_READY)
    );

    // DECODER INSTANCE
    decoder decode (
	    .byte_ready(BYTE_READY),
	    .command_byte(COMMAND_BYTE),
	    .toggle_mask(TOGGLE_MASK)
    );

    // PIN CONTROLLER INSTANCE
    pin_controller pin_ctrl(
	    .clk(CLK),
	    .toggle_mask(TOGGLE_MASK),
	    .toggle_enable(BYTE_READY),
	    .output_pins(pins)
    );

endmodule

icoboard/ver1/tb/top_tb.v
`timescale 1ns / 1ps

module top_tb;

    // Inputs
    reg CLK = 0;         // System clock (internal logic)
    reg SCLK = 0;        // SPI clock
    reg CS = 1;          // Chip select (active low)
    reg MOSI = 0;        // SPI data

    // Output
    wire [63:0] pins;  // Output from pin controller

    // Instantiate the top module
    top uut (
        .CLK(CLK),
        .SCLK(SCLK),
        .CS(CS),
        .MOSI(MOSI),
        .pins(pins)
    );

    // Generate system clock (100 MHz)
    initial CLK = 0;
    always #5 CLK = ~CLK;

    // Task to send a single SPI byte (MSB first)
    task send_spi_byte(input [7:0] data);
        integer i;
        begin
            #5;

            for (i = 7; i >= 0; i = i - 1) begin
		SCLK = 0;
                #10;
		MOSI = data[i];

                SCLK = 1;
                #10;
            end

	    SCLK = 0;
	    #40;
        end
    endtask

    initial begin
        $display("Starting top module testbench...");
        $dumpfile("top_tb.vcd");
        $dumpvars(0, top_tb);

        // Initialize inputs
        CS = 1;
        #40;
	CS = 0;

        send_spi_byte(8'h00);   // Toggle pin 0 ON
	#40;

        send_spi_byte(8'h00);   // Toggle pin 0 OFF
	#40;

        send_spi_byte(8'h03);   // Toggle pin 3 ON
	#40;

        send_spi_byte(8'h3F);   // Toggle pin 63 ON
	#40;
	
        send_spi_byte(8'h3F);   // Toggle pin 63 OFF
        #1000;
	CS = 1;
	#40;
        $display("Final pins = %b", pins);
        $finish;
    end

endmodule

icoboard/ver1/tb/top_tb.vcd
$date
	Wed Apr  9 14:10:22 2025
$end
$version
	Icarus Verilog
$end
$timescale
	1ps
$end
$scope module top_tb $end
$var wire 64 ! pins [63:0] $end
$var reg 1 " CLK $end
$var reg 1 # CS $end
$var reg 1 $ MOSI $end
$var reg 1 % SCLK $end
$scope module uut $end
$var wire 1 " CLK $end
$var wire 1 # CS $end
$var wire 1 $ MOSI $end
$var wire 1 % SCLK $end
$var wire 64 & pins [63:0] $end
$var wire 64 ' TOGGLE_MASK [63:0] $end
$var wire 8 ( COMMAND_BYTE [7:0] $end
$var wire 1 ) BYTE_READY $end
$scope module decode $end
$var wire 8 * command_byte [7:0] $end
$var wire 1 ) byte_ready $end
$var reg 64 + toggle_mask [63:0] $end
$upscope $end
$scope module pin_ctrl $end
$var wire 1 " clk $end
$var wire 64 , toggle_mask [63:0] $end
$var wire 1 ) toggle_enable $end
$var reg 64 - output_pins [63:0] $end
$var reg 1 . prev_toggle_enable $end
$upscope $end
$scope module spi_receiver $end
$var wire 1 # cs $end
$var wire 1 $ mosi $end
$var wire 1 % sclk $end
$var reg 3 / bit_count [2:0] $end
$var reg 1 ) byte_ready $end
$var reg 8 0 command_byte [7:0] $end
$upscope $end
$upscope $end
$scope task send_spi_byte $end
$var reg 8 1 data [7:0] $end
$var integer 32 2 i [31:0] $end
$upscope $end
$upscope $end
$enddefinitions $end
#0
$dumpvars
bx 2
bx 1
bx0 0
bx /
x.
b0 -
bx ,
bx +
bx0 *
0)
bx0 (
bx '
b0 &
0%
0$
1#
0"
b0 !
$end
#5000
0.
1"
#10000
0"
#15000
1"
#20000
0"
#25000
1"
#30000
0"
#35000
1"
#40000
b0 /
0"
b0 1
0#
#45000
1"
b111 2
#50000
0"
#55000
1"
1%
#60000
0"
#65000
b1 /
bx00 (
bx00 *
bx00 0
1"
0%
b110 2
#70000
0"
#75000
1"
1%
#80000
0"
#85000
b10 /
bx000 (
bx000 *
bx000 0
1"
0%
b101 2
#90000
0"
#95000
1"
1%
#100000
0"
#105000
b11 /
bx0000 (
bx0000 *
bx0000 0
1"
0%
b100 2
#110000
0"
#115000
1"
1%
#120000
0"
#125000
b100 /
bx00000 (
bx00000 *
bx00000 0
1"
0%
b11 2
#130000
0"
#135000
1"
1%
#140000
0"
#145000
b101 /
bx000000 (
bx000000 *
bx000000 0
1"
0%
b10 2
#150000
0"
#155000
1"
1%
#160000
0"
#165000
b110 /
bx0000000 (
bx0000000 *
bx0000000 0
1"
0%
b1 2
#170000
0"
#175000
1"
1%
#180000
0"
#185000
b111 /
b0 (
b0 *
b0 0
1"
0%
b0 2
#190000
0"
#195000
1"
1%
#200000
0"
#205000
b1 '
b1 +
b1 ,
1)
b0 /
1"
0%
b11111111111111111111111111111111 2
#210000
0"
#215000
1.
b1 !
b1 &
b1 -
1"
#220000
0"
#225000
1"
#230000
0"
#235000
1"
#240000
0"
#245000
1"
#250000
0"
#255000
1"
#260000
0"
#265000
1"
#270000
0"
#275000
1"
#280000
0"
#285000
1"
#290000
0"
b111 2
#295000
1"
#300000
0"
1%
#305000
1"
#310000
0)
b1 /
0"
0%
b110 2
#315000
0.
1"
#320000
0"
1%
#325000
1"
#330000
b10 /
0"
0%
b101 2
#335000
1"
#340000
0"
1%
#345000
1"
#350000
b11 /
0"
0%
b100 2
#355000
1"
#360000
0"
1%
#365000
1"
#370000
b100 /
0"
0%
b11 2
#375000
1"
#380000
0"
1%
#385000
1"
#390000
b101 /
0"
0%
b10 2
#395000
1"
#400000
0"
1%
#405000
1"
#410000
b110 /
0"
0%
b1 2
#415000
1"
#420000
0"
1%
#425000
1"
#430000
b111 /
0"
0%
b0 2
#435000
1"
#440000
0"
1%
#445000
1"
#450000
1)
b0 /
0"
0%
b11111111111111111111111111111111 2
#455000
1.
b0 !
b0 &
b0 -
1"
#460000
0"
#465000
1"
#470000
0"
#475000
1"
#480000
0"
#485000
1"
#490000
0"
#495000
1"
#500000
0"
#505000
1"
#510000
0"
#515000
1"
#520000
0"
#525000
1"
#530000
0"
b11 1
#535000
1"
b111 2
#540000
0"
#545000
1"
1%
#550000
0"
#555000
0)
b1 /
1"
0%
b110 2
#560000
0"
#565000
0.
1"
1%
#570000
0"
#575000
b10 /
1"
0%
b101 2
#580000
0"
#585000
1"
1%
#590000
0"
#595000
b11 /
1"
0%
b100 2
#600000
0"
#605000
1"
1%
#610000
0"
#615000
b100 /
1"
0%
b11 2
#620000
0"
#625000
1"
1%
#630000
0"
#635000
b101 /
1"
0%
b10 2
#640000
0"
#645000
1"
1%
#650000
0"
#655000
b110 /
1"
0%
b1 2
#660000
0"
#665000
1"
1%
1$
#670000
0"
#675000
b111 /
b1 (
b1 *
b1 0
1"
0%
b0 2
#680000
0"
#685000
1"
1%
#690000
0"
#695000
b1000 '
b1000 +
b1000 ,
1)
b0 /
b11 (
b11 *
b11 0
1"
0%
b11111111111111111111111111111111 2
#700000
0"
#705000
1.
b1000 !
b1000 &
b1000 -
1"
#710000
0"
#715000
1"
#720000
0"
#725000
1"
#730000
0"
#735000
1"
#740000
0"
#745000
1"
#750000
0"
#755000
1"
#760000
0"
#765000
1"
#770000
0"
#775000
1"
b111111 1
#780000
0"
b111 2
#785000
1"
#790000
0"
1%
0$
#795000
1"
#800000
0)
b1 /
b110 (
b110 *
b110 0
0"
0%
b110 2
#805000
0.
1"
#810000
0"
1%
#815000
1"
#820000
b10 /
b1100 (
b1100 *
b1100 0
0"
0%
b101 2
#825000
1"
#830000
0"
1%
1$
#835000
1"
#840000
b11 /
b11001 (
b11001 *
b11001 0
0"
0%
b100 2
#845000
1"
#850000
0"
1%
#855000
1"
#860000
b100 /
b110011 (
b110011 *
b110011 0
0"
0%
b11 2
#865000
1"
#870000
0"
1%
#875000
1"
#880000
b101 /
b1100111 (
b1100111 *
b1100111 0
0"
0%
b10 2
#885000
1"
#890000
0"
1%
#895000
1"
#900000
b110 /
b11001111 (
b11001111 *
b11001111 0
0"
0%
b1 2
#905000
1"
#910000
0"
1%
#915000
1"
#920000
b111 /
b10011111 (
b10011111 *
b10011111 0
0"
0%
b0 2
#925000
1"
#930000
0"
1%
#935000
1"
#940000
b1000000000000000000000000000000000000000000000000000000000000000 '
b1000000000000000000000000000000000000000000000000000000000000000 +
b1000000000000000000000000000000000000000000000000000000000000000 ,
1)
b0 /
b111111 (
b111111 *
b111111 0
0"
0%
b11111111111111111111111111111111 2
#945000
1.
b1000000000000000000000000000000000000000000000000000000000001000 !
b1000000000000000000000000000000000000000000000000000000000001000 &
b1000000000000000000000000000000000000000000000000000000000001000 -
1"
#950000
0"
#955000
1"
#960000
0"
#965000
1"
#970000
0"
#975000
1"
#980000
0"
#985000
1"
#990000
0"
#995000
1"
#1000000
0"
#1005000
1"
#1010000
0"
#1015000
1"
#1020000
0"
#1025000
1"
b111 2
#1030000
0"
#1035000
1"
1%
0$
#1040000
0"
#1045000
0)
b1 /
b1111110 (
b1111110 *
b1111110 0
1"
0%
b110 2
#1050000
0"
#1055000
0.
1"
1%
#1060000
0"
#1065000
b10 /
b11111100 (
b11111100 *
b11111100 0
1"
0%
b101 2
#1070000
0"
#1075000
1"
1%
1$
#1080000
0"
#1085000
b11 /
b11111001 (
b11111001 *
b11111001 0
1"
0%
b100 2
#1090000
0"
#1095000
1"
1%
#1100000
0"
#1105000
b100 /
b11110011 (
b11110011 *
b11110011 0
1"
0%
b11 2
#1110000
0"
#1115000
1"
1%
#1120000
0"
#1125000
b101 /
b11100111 (
b11100111 *
b11100111 0
1"
0%
b10 2
#1130000
0"
#1135000
1"
1%
#1140000
0"
#1145000
b110 /
b11001111 (
b11001111 *
b11001111 0
1"
0%
b1 2
#1150000
0"
#1155000
1"
1%
#1160000
0"
#1165000
b111 /
b10011111 (
b10011111 *
b10011111 0
1"
0%
b0 2
#1170000
0"
#1175000
1"
1%
#1180000
0"
#1185000
1)
b0 /
b111111 (
b111111 *
b111111 0
1"
0%
b11111111111111111111111111111111 2
#1190000
0"
#1195000
1.
b1000 !
b1000 &
b1000 -
1"
