SPI/8bit_echo/spi_slave.v
module spi_slave (
    input  wire sclk,  // SPI clock
    input  wire cs,    // Chip select (active low)
    input  wire mosi,  // Master Out, Slave In
    output reg miso    // Master In, Slave Out
);
	reg [7:0] shift_reg = 8'hAA;
	reg [7:0] received_data;

	always @(negedge sclk) begin
		if (!cs) begin
			shift_reg <= {shift_reg[6:0], mosi};
		end
	end

	always @(posedge sclk) begin
		if (!cs) begin
			miso <= received_data[7];
			received_data <= {received_data[6:0], 1'b0};
		end
	end

	always @(posedge cs) begin
		received_data <= shift_reg;
		shift_reg <= 8'h00;
	end
endmodule

old/8bit_echo/tb/spi_slave_tb.v
`timescale 1ns/1ps

module spi_slave_tb;
    reg sclk = 0;
    reg cs = 1;
    reg mosi = 0;
    reg [2:0] counter= 0;
    reg [7:0] mosi_data;
    wire miso;
    integer i;

    // Instantiate SPI Slave
    spi_slave uut (
        .sclk(sclk),
        .cs(cs),
        .mosi(mosi),
        .miso(miso)
    );

    always @(negedge cs) begin
	    for (i = 0; i < 16; i = i + 1) begin
		    #10 sclk = ~sclk;
	    end
//	    while (!cs) begin
//		    sclk = ~sclk;
//	    end
    end

    always @(posedge sclk) begin
	    if (counter < 8) begin
		    mosi <= mosi_data[7 - counter];
		    counter <= counter + 1;
	    end else begin
		    counter <= 0;
	    end
    end


    initial begin
	    $dumpfile("spi_slave_tb.vcd");  // Create waveform file for GTKWave
	    $dumpvars(0, spi_slave_tb);    // Dump all signals

	    // Send first byte (0x00)
	    #20
	    mosi_data = 8'h00;
	    cs = 0;
	    #170;
	    cs = 1;

	    #80
	    mosi_data = 8'hA5;
	    cs = 0;
	    #170;
	    cs = 1;

	    #80
	    mosi_data = 8'h3C;
	    cs = 0;
	    #170;
	    cs = 1;

	    #80
	    mosi_data = 8'h7F;
	    cs = 0;
	    #170;
	    cs = 1;

	    #40 $finish;
    end
endmodule

SPI/8bit_echo/spi_slave_tb.vcd
$date
	Sat Mar  1 21:03:53 2025
$end
$version
	Icarus Verilog
$end
$timescale
	1ps
$end
$scope module spi_slave_tb $end
$var wire 1 ! miso $end
$var reg 3 " counter [2:0] $end
$var reg 1 # cs $end
$var reg 1 $ mosi $end
$var reg 8 % mosi_data [7:0] $end
$var reg 1 & sclk $end
$var integer 32 ' i [31:0] $end
$scope module uut $end
$var wire 1 # cs $end
$var wire 1 $ mosi $end
$var wire 1 & sclk $end
$var reg 1 ! miso $end
$var reg 8 ( received_data [7:0] $end
$var reg 8 ) shift_reg [7:0] $end
$upscope $end
$upscope $end
$enddefinitions $end
#0
$dumpvars
b0 )
b10101010 (
bx '
0&
bx %
0$
1#
b0 "
x!
$end
#20000
b0 '
0#
b0 %
#30000
b1010100 (
1!
b1 "
b1 '
1&
#40000
b10 '
0&
#50000
b10 "
b10101000 (
0!
b11 '
1&
#60000
b100 '
0&
#70000
b1010000 (
1!
b11 "
b101 '
1&
#80000
b110 '
0&
#90000
b100 "
b10100000 (
0!
b111 '
1&
#100000
b1000 '
0&
#110000
b1000000 (
1!
b101 "
b1001 '
1&
#120000
b1010 '
0&
#130000
b110 "
b10000000 (
0!
b1011 '
1&
#140000
b1100 '
0&
#150000
b0 (
1!
b111 "
b1101 '
1&
#160000
b1110 '
0&
#170000
b0 "
0!
b1111 '
1&
#180000
b10000 '
0&
#190000
1#
#270000
b0 '
0#
b10100101 %
#280000
b1 "
1$
b1 '
1&
#290000
b1 )
b10 '
0&
#300000
b10 "
0$
b11 '
1&
#310000
b10 )
b100 '
0&
#320000
b11 "
1$
b101 '
1&
#330000
b101 )
b110 '
0&
#340000
b100 "
0$
b111 '
1&
#350000
b1010 )
b1000 '
0&
#360000
b101 "
b1001 '
1&
#370000
b10100 )
b1010 '
0&
#380000
b110 "
1$
b1011 '
1&
#390000
b101001 )
b1100 '
0&
#400000
b111 "
0$
b1101 '
1&
#410000
b1010010 )
b1110 '
0&
#420000
b0 "
1$
b1111 '
1&
#430000
b10100101 )
b10000 '
0&
#440000
b0 )
b10100101 (
1#
#520000
b0 '
0#
b111100 %
#530000
b1001010 (
1!
b1 "
0$
b1 '
1&
#540000
b10 '
0&
#550000
b10 "
b10010100 (
0!
b11 '
1&
#560000
b100 '
0&
#570000
b101000 (
1!
b11 "
1$
b101 '
1&
#580000
b1 )
b110 '
0&
#590000
b100 "
b1010000 (
0!
b111 '
1&
#600000
b11 )
b1000 '
0&
#610000
b10100000 (
b101 "
b1001 '
1&
#620000
b111 )
b1010 '
0&
#630000
b110 "
b1000000 (
1!
b1011 '
1&
#640000
b1111 )
b1100 '
0&
#650000
b10000000 (
0!
b111 "
0$
b1101 '
1&
#660000
b11110 )
b1110 '
0&
#670000
b0 "
b0 (
1!
b1111 '
1&
#680000
b111100 )
b10000 '
0&
#690000
b0 )
b111100 (
1#
#770000
b0 '
0#
b1111111 %
#780000
b1111000 (
0!
b1 "
b1 '
1&
#790000
b10 '
0&
#800000
b10 "
1$
b11110000 (
b11 '
1&
#810000
b1 )
b100 '
0&
#820000
b11100000 (
1!
b11 "
b101 '
1&
#830000
b11 )
b110 '
0&
#840000
b100 "
b11000000 (
b111 '
1&
#850000
b111 )
b1000 '
0&
#860000
b10000000 (
b101 "
b1001 '
1&
#870000
b1111 )
b1010 '
0&
#880000
b110 "
b0 (
b1011 '
1&
#890000
b11111 )
b1100 '
0&
#900000
0!
b111 "
b1101 '
1&
#910000
b111111 )
b1110 '
0&
#920000
b0 "
b1111 '
1&
#930000
b1111111 )
b10000 '
0&
#940000
b0 )
b1111111 (
1#
